{
  "type": "FeatureCollection",
  "generated_at": "2026-05-25T00:14:22+00:00",
  "features": [
    {
      "type": "Feature",
      "geometry": {
        "type": "Point",
        "coordinates": [
          8.68479061126709,
          46.99063491821289
        ]
      },
      "properties": {
        "egrid": "CH432277405797",
        "canton": "SZ",
        "commune": "1944",
        "bfs_nr": "1367",
        "parcel_nr": "1944",
        "owner": null,
        "owner_address": null,
        "herrenlos_type": "dereliktion",
        "claim_possible": 1,
        "scanned_at": "2026-05-23 16:27:57"
      }
    },
    {
      "type": "Feature",
      "geometry": {
        "type": "Point",
        "coordinates": [
          8.68479061126709,
          46.99063491821289
        ]
      },
      "properties": {
        "egrid": "CH444022775711",
        "canton": "SZ",
        "commune": "2064",
        "bfs_nr": "1367",
        "parcel_nr": "2064",
        "owner": null,
        "owner_address": null,
        "herrenlos_type": "dereliktion",
        "claim_possible": 1,
        "scanned_at": "2026-05-23 16:27:53"
      }
    }
  ]
}