{
  "type": "FeatureCollection",
  "generated_at": "2026-05-29T21:34:22+00:00",
  "features": [
    {
      "type": "Feature",
      "geometry": {
        "type": "Point",
        "coordinates": [
          8.719454765319824,
          47.17441177368164
        ]
      },
      "properties": {
        "egrid": "CH184226387886",
        "canton": "SZ",
        "commune": "SZ0200001321",
        "bfs_nr": "1321",
        "parcel_nr": "1274",
        "owner": null,
        "owner_address": null,
        "herrenlos_type": "dereliktion",
        "claim_possible": 1,
        "scanned_at": "2026-05-29 16:24:31"
      }
    }
  ]
}