{
  "type": "FeatureCollection",
  "generated_at": "2026-05-29T12:26:11+00:00",
  "features": [
    {
      "type": "Feature",
      "geometry": {
        "type": "Point",
        "coordinates": [
          9.702816009521484,
          46.93720626831055
        ]
      },
      "properties": {
        "egrid": "CH189274917786",
        "canton": "GR",
        "commune": "GR0000003863",
        "bfs_nr": "3863",
        "parcel_nr": "803",
        "owner": null,
        "owner_address": null,
        "herrenlos_type": "not_in_grundbuch",
        "claim_possible": 0,
        "scanned_at": "2026-05-28 10:01:14"
      }
    }
  ]
}