{
  "type": "FeatureCollection",
  "generated_at": "2026-05-30T00:23:46+00:00",
  "features": [
    {
      "type": "Feature",
      "geometry": {
        "type": "Point",
        "coordinates": [
          6.93482780456543,
          46.90528869628906
        ]
      },
      "properties": {
        "egrid": "CH450510789470",
        "canton": "FR",
        "commune": "Gletterens",
        "bfs_nr": "2022",
        "parcel_nr": "554",
        "owner": null,
        "owner_address": null,
        "herrenlos_type": "not_in_grundbuch",
        "claim_possible": 0,
        "scanned_at": "2026-05-29 22:00:02"
      }
    },
    {
      "type": "Feature",
      "geometry": {
        "type": "Point",
        "coordinates": [
          6.974939346313477,
          46.701541900634766
        ]
      },
      "properties": {
        "egrid": "CH167285019568",
        "canton": "FR",
        "commune": "Massonnens",
        "bfs_nr": "2086",
        "parcel_nr": "553",
        "owner": null,
        "owner_address": null,
        "herrenlos_type": "not_in_grundbuch",
        "claim_possible": 0,
        "scanned_at": "2026-05-29 22:11:18"
      }
    },
    {
      "type": "Feature",
      "geometry": {
        "type": "Point",
        "coordinates": [
          6.977141380310059,
          46.69842529296875
        ]
      },
      "properties": {
        "egrid": "CH980885017227",
        "canton": "FR",
        "commune": "Massonnens",
        "bfs_nr": "2086",
        "parcel_nr": "583",
        "owner": null,
        "owner_address": null,
        "herrenlos_type": "not_in_grundbuch",
        "claim_possible": 0,
        "scanned_at": "2026-05-29 22:00:13"
      }
    },
    {
      "type": "Feature",
      "geometry": {
        "type": "Point",
        "coordinates": [
          8.719454765319824,
          47.17441177368164
        ]
      },
      "properties": {
        "egrid": "CH184226387886",
        "canton": "SZ",
        "commune": "SZ0200001321",
        "bfs_nr": "1321",
        "parcel_nr": "1274",
        "owner": null,
        "owner_address": null,
        "herrenlos_type": "dereliktion",
        "claim_possible": 1,
        "scanned_at": "2026-05-29 16:24:31"
      }
    },
    {
      "type": "Feature",
      "geometry": {
        "type": "Point",
        "coordinates": [
          8.49510383605957,
          47.718624114990234
        ]
      },
      "properties": {
        "egrid": "CH392677393844",
        "canton": "SZ",
        "commune": "SZ0200001322",
        "bfs_nr": "1322",
        "parcel_nr": "1413",
        "owner": null,
        "owner_address": null,
        "herrenlos_type": "dereliktion",
        "claim_possible": 1,
        "scanned_at": "2026-05-29 20:28:35"
      }
    },
    {
      "type": "Feature",
      "geometry": {
        "type": "Point",
        "coordinates": [
          8.726723670959473,
          47.196781158447266
        ]
      },
      "properties": {
        "egrid": "CH327880263892",
        "canton": "SZ",
        "commune": "SZ0200001322",
        "bfs_nr": "1322",
        "parcel_nr": "3529",
        "owner": null,
        "owner_address": null,
        "herrenlos_type": "dereliktion",
        "claim_possible": 1,
        "scanned_at": "2026-05-29 20:27:54"
      }
    }
  ]
}